chistesESP/__init__.py
chistesESP-0.0.2.dist-info/METADATA
chistesESP-0.0.2.dist-info/RECORD
chistesESP-0.0.2.dist-info/WHEEL
chistesESP-0.0.2.dist-info/top_level.txt
