Metadata-Version: 2.1
Name: chistesESP
Version: 0.0.2
Summary: Un paquete que contiene un comando que obtiene chistes de chistes.com
Home-page: https://github.com/netherpills/chistesESP-py
Author: netherpills
Author-email: mari394334@gmail.com
License: UNKNOWN
Platform: UNKNOWN
Classifier: Programming Language :: Python :: 3
Classifier: License :: OSI Approved :: MIT License
Classifier: Operating System :: OS Independent
Requires-Python: >=3.6
